pyarmor/cli/core/alpine/__init__.py
pyarmor/cli/core/alpine/aarch64/pyarmor_runtime.so
pyarmor/cli/core/alpine/aarch64/pytransform3.so
pyarmor/cli/core/alpine/mips32el/pyarmor_runtime.so
pyarmor/cli/core/alpine/mips32el/pytransform3.so
pyarmor/cli/core/alpine/mips64el/pyarmor_runtime.so
pyarmor/cli/core/alpine/mips64el/pytransform3.so
pyarmor/cli/core/alpine/ppc64le/pyarmor_runtime.so
pyarmor/cli/core/alpine/ppc64le/pytransform3.so
pyarmor/cli/core/alpine/x86_64/pyarmor_runtime.so
pyarmor/cli/core/alpine/x86_64/pytransform3.so
pyarmor_cli_core_alpine-7.6.8.dist-info/METADATA
pyarmor_cli_core_alpine-7.6.8.dist-info/WHEEL
pyarmor_cli_core_alpine-7.6.8.dist-info/top_level.txt
pyarmor_cli_core_alpine-7.6.8.dist-info/RECORD
